{
  "resources":{
  "includes":[{
    "pattern":"\\QMETA-INF/io.netty.versions.properties\\E"
  }, {
    "pattern":"\\QMETA-INF/microprofile-config.properties\\E"
  }, {
    "pattern":"\\QMETA-INF/native/libnetty_transport_native_epoll_x86_64.so\\E"
  }, {
    "pattern":"\\QMETA-INF/services/io.grpc.LoadBalancerProvider\\E"
  }, {
    "pattern":"\\QMETA-INF/services/io.grpc.NameResolverProvider\\E"
  }, {
    "pattern":"\\QMETA-INF/services/io.quarkus.arc.ComponentsProvider\\E"
  }, {
    "pattern":"\\QMETA-INF/services/io.quarkus.arc.ResourceReferenceProvider\\E"
  }, {
    "pattern":"\\QMETA-INF/services/io.quarkus.grpc.spi.GrpcBuilderProvider\\E"
  }, {
    "pattern":"\\QMETA-INF/services/io.smallrye.context.storage.spi.StorageManagerProvider\\E"
  }, {
    "pattern":"\\QMETA-INF/services/io.smallrye.mutiny.infrastructure.CallbackDecorator\\E"
  }, {
    "pattern":"\\QMETA-INF/services/io.smallrye.mutiny.infrastructure.ExecutorConfiguration\\E"
  }, {
    "pattern":"\\QMETA-INF/services/io.smallrye.mutiny.infrastructure.MultiInterceptor\\E"
  }, {
    "pattern":"\\QMETA-INF/services/io.smallrye.mutiny.infrastructure.UniInterceptor\\E"
  }, {
    "pattern":"\\QMETA-INF/services/io.smallrye.stork.spi.config.ConfigProvider\\E"
  }, {
    "pattern":"\\QMETA-INF/services/io.smallrye.stork.spi.internal.LoadBalancerLoader\\E"
  }, {
    "pattern":"\\QMETA-INF/services/io.smallrye.stork.spi.internal.ServiceDiscoveryLoader\\E"
  }, {
    "pattern":"\\QMETA-INF/services/io.smallrye.stork.spi.internal.ServiceRegistrarLoader\\E"
  }, {
    "pattern":"\\QMETA-INF/services/io.vertx.core.spi.VerticleFactory\\E"
  }, {
    "pattern":"\\QMETA-INF/services/io.vertx.core.spi.VertxServiceProvider\\E"
  }, {
    "pattern":"\\QMETA-INF/services/java.lang.System$LoggerFinder\\E"
  }, {
    "pattern":"\\QMETA-INF/services/java.net.spi.InetAddressResolverProvider\\E"
  }, {
    "pattern":"\\QMETA-INF/services/java.nio.channels.spi.SelectorProvider\\E"
  }, {
    "pattern":"\\QMETA-INF/services/java.nio.file.spi.FileSystemProvider\\E"
  }, {
    "pattern":"\\QMETA-INF/services/org.eclipse.microprofile.config.spi.ConfigProviderResolver\\E"
  }, {
    "pattern":"\\QMETA-INF/services/org.jboss.logging.LoggerProvider\\E"
  }, {
    "pattern":"\\QMETA-INF/services/org.jboss.logmanager.ConfiguratorFactory\\E"
  }, {
    "pattern":"\\QMETA-INF/services/org.jboss.logmanager.LogContextConfigurator\\E"
  }, {
    "pattern":"\\QMETA-INF/services/org.jboss.logmanager.LogContextInitializer\\E"
  }, {
    "pattern":"\\QMETA-INF/services/org.jboss.logmanager.MDCProvider\\E"
  }, {
    "pattern":"\\QMETA-INF/services/org.jboss.logmanager.NDCProvider\\E"
  }, {
    "pattern":"\\QMETA-INF/services/org.slf4j.spi.SLF4JServiceProvider\\E"
  }, {
    "pattern":"\\QMETA-INF/services/org/apache/activemq/transport/tcp\\E"
  }, {
    "pattern":"\\QMETA-INF/services/org/apache/activemq/wireformat/default\\E"
  }, {
    "pattern":"\\Qapplication.properties\\E"
  }, {
    "pattern":"\\Qlogging.properties\\E"
  }, {
    "pattern":"\\Qorg/jboss/threads/Version.properties\\E"
  }]},
  "bundles":[]
}
